aioroku/__init__.py
aioroku/core.py
aioroku/example.py
aioroku-1.0.0.dist-info/LICENSE
aioroku-1.0.0.dist-info/WHEEL
aioroku-1.0.0.dist-info/METADATA
aioroku-1.0.0.dist-info/RECORD
