Metadata-Version: 2.1
Name: aioroku
Version: 1.0.0
Summary: Asynchronous library to the Roku media player. Easy, breezy, beautiful.
Home-page: https://gitlab.com/pancho-villa/aioroku
License: UNKNOWN
Author: Adam Garcia
Author-email: garciadam@gmail.com
Classifier: License :: OSI Approved :: MIT License
Requires-Dist: aiohttp
